<root>
    <item name='org.openqa.selenium.WebDriver org.openqa.selenium.WebElement findElement(org.openqa.selenium.By)'>
        <annotation name='org.jetbrains.annotations.Contract'>
            <val name="pure" val="true"/>
        </annotation>
    </item>
    <item name='org.openqa.selenium.WebDriver.TargetLocator org.openqa.selenium.Alert alert()'>
        <annotation name='org.jetbrains.annotations.Contract'>
            <val name="pure" val="true"/>
        </annotation>
    </item>
</root>